opp/__init__.py
opp/c2pa.py
opp/cli.py
opp/decorators.py
opp/graph.py
opp/merkle.py
opp/odin_shim.py
opp/util.py
opp/schemas/opp.step.v1.json
opp_py-0.1.1.dist-info/METADATA
opp_py-0.1.1.dist-info/WHEEL
opp_py-0.1.1.dist-info/entry_points.txt
opp_py-0.1.1.dist-info/top_level.txt
opp_py-0.1.1.dist-info/RECORD
