Metadata-Version: 2.4
Name: opp-py
Version: 0.1.1
Summary: ODIN Provenance Passport — Python instrumentation + CLI
Author: Maverick0351a
License-Expression: Apache-2.0
Project-URL: Homepage, https://github.com/Maverick0351a/opp-provenance-passport
Project-URL: Repository, https://github.com/Maverick0351a/opp-provenance-passport
Project-URL: Issues, https://github.com/Maverick0351a/opp-provenance-passport/issues
Project-URL: Documentation, https://github.com/Maverick0351a/opp-provenance-passport#readme
Keywords: provenance,ai,model passport,odin,ope,c2pa,policy
Classifier: Programming Language :: Python :: 3
Classifier: Programming Language :: Python :: 3.10
Classifier: Programming Language :: Python :: 3.11
Classifier: Operating System :: OS Independent
Classifier: Intended Audience :: Developers
Classifier: Topic :: Security :: Cryptography
Classifier: Topic :: Software Development :: Libraries
Requires-Python: >=3.10
Requires-Dist: httpx>=0.27.0
Requires-Dist: cryptography>=43.0.1
Requires-Dist: typer>=0.12.4
